ebdesk_email_executor/.DS_Store
ebdesk_email_executor/__init__.py
ebdesk_email_executor/config/__init__.py
ebdesk_email_executor/config/mongo.py
ebdesk_email_executor/config/redis.py
ebdesk_email_executor/main.py
ebdesk_email_executor/model/__init__.py
ebdesk_email_executor/model/base.py
ebdesk_email_executor/route/__init__.py
ebdesk_email_executor/route/email.py
ebdesk_email_executor-0.1.27.dist-info/WHEEL
ebdesk_email_executor-0.1.27.dist-info/METADATA
ebdesk_email_executor-0.1.27.dist-info/RECORD
