Metadata-Version: 2.1
Name: ebdesk-email-executor
Version: 0.1.27
Summary: 
Author: Nasri Adzlani
Author-email: nasri@jkt1.ebdesk.com
Requires-Python: >=3.10,<4.0
Classifier: Programming Language :: Python :: 3
Classifier: Programming Language :: Python :: 3.10
Classifier: Programming Language :: Python :: 3.11
Requires-Dist: pymongo (>=4.0.1,<5.0.0)
Requires-Dist: redis (>=4.5.5,<5.0.0)
Requires-Dist: uvicorn (>=0.17.4,<0.18.0)
